<?xml version="1.0" encoding="UTF-8"?>
<item><name><![CDATA[2004 Season Photos]]></name><id><![CDATA[4d8f578f909de]]></id><images><image caption="Nov. 7, 2004"><![CDATA[bang011.jpg]]></image><image caption="Nov. 7, 2004"><![CDATA[bang021.jpg]]></image><image caption="Nov. 7, 2004"><![CDATA[bang031.jpg]]></image><image caption="Nov. 7, 2004"><![CDATA[bang041.jpg]]></image><image caption="Nov. 7, 2004"><![CDATA[bang051.jpg]]></image><image caption="Nov. 7, 2004"><![CDATA[bang061.jpg]]></image><image caption="Nov. 7, 2004"><![CDATA[bang071.jpg]]></image></images></item>
